HISTORY.rst
LICENSE
MANIFEST.in
NOTICE
README.rst
setup.py
requesocks/__init__.py
requesocks/api.py
requesocks/async.py
requesocks/auth.py
requesocks/compat.py
requesocks/defaults.py
requesocks/exceptions.py
requesocks/hooks.py
requesocks/models.py
requesocks/sessions.py
requesocks/status_codes.py
requesocks/structures.py
requesocks/utils.py
requesocks.egg-info/PKG-INFO
requesocks.egg-info/SOURCES.txt
requesocks.egg-info/dependency_links.txt
requesocks.egg-info/requires.txt
requesocks.egg-info/top_level.txt
requesocks/packages/__init__.py
requesocks/packages/oreos/__init__.py
requesocks/packages/oreos/core.py
requesocks/packages/oreos/monkeys.py
requesocks/packages/oreos/structures.py
requesocks/packages/urllib3/__init__.py
requesocks/packages/urllib3/_collections.py
requesocks/packages/urllib3/connectionpool.py
requesocks/packages/urllib3/exceptions.py
requesocks/packages/urllib3/filepost.py
requesocks/packages/urllib3/poolmanager.py
requesocks/packages/urllib3/request.py
requesocks/packages/urllib3/response.py
requesocks/packages/urllib3/packages/__init__.py
requesocks/packages/urllib3/packages/six.py
requesocks/packages/urllib3/packages/mimetools_choose_boundary/__init__.py
requesocks/packages/urllib3/packages/socksipy/__init__.py
requesocks/packages/urllib3/packages/socksipy/socks.py
requesocks/packages/urllib3/packages/socksipy/socksipyhandler.py
requesocks/packages/urllib3/packages/ssl_match_hostname/__init__.py